{
  "results": [
    {
      "command": "Oxiflex Problems/queens/minizinc/datafiles/8.fzn -n -r",
      "mean": 0.001883931980649822,
      "stddev": 0.0006936349580994369,
      "median": 0.0017104201200000002,
      "user": 0.0015607393646209367,
      "system": 0.00034873244765342944,
      "min": 0.0010662281200000002,
      "max": 0.006244913120000001,
      "parameters": {
        "n": "8"
      }
    },
    {
      "command": "Oxiflex Problems/queens/minizinc/datafiles/8.fzn -n",
      "mean": 0.002872363828641976,
      "stddev": 0.000496773836591933,
      "median": 0.00266669112,
      "user": 0.0024820277530864187,
      "system": 0.00041356797530864195,
      "min": 0.0024129661200000003,
      "max": 0.004898457120000001,
      "parameters": {
        "n": "8"
      }
    },
    {
      "command": "Oxiflex Problems/queens/minizinc/datafiles/8.fzn -f -r",
      "mean": 0.002236015796540285,
      "stddev": 0.0006614524616966338,
      "median": 0.0020431546200000003,
      "user": 0.0018955968246445504,
      "system": 0.000361101421800948,
      "min": 0.0014887421200000003,
      "max": 0.006236914120000001,
      "parameters": {
        "n": "8"
      }
    },
    {
      "command": "Oxiflex Problems/queens/minizinc/datafiles/8.fzn -f",
      "mean": 0.0041744870175155335,
      "stddev": 0.0006970638444029982,
      "median": 0.0038746386200000003,
      "user": 0.0036481823913043425,
      "system": 0.0005550505279503105,
      "min": 0.0035164361200000003,
      "max": 0.0067539231200000015,
      "parameters": {
        "n": "8"
      }
    },
    {
      "command": "Oxiflex Problems/queens/minizinc/datafiles/10.fzn -n -r",
      "mean": 0.005753368569230768,
      "stddev": 0.00514130752421718,
      "median": 0.003926361120000001,
      "user": 0.005233432307692305,
      "system": 0.0005399131076923076,
      "min": 0.0015261831200000004,
      "max": 0.03354343012,
      "parameters": {
        "n": "10"
      }
    },
    {
      "command": "Oxiflex Problems/queens/minizinc/datafiles/10.fzn -n",
      "mean": 0.004467193281061949,
      "stddev": 0.0007002382623283912,
      "median": 0.00419950612,
      "user": 0.0038786026194690256,
      "system": 0.0006146370619469023,
      "min": 0.00383296112,
      "max": 0.007337281120000001,
      "parameters": {
        "n": "10"
      }
    },
    {
      "command": "Oxiflex Problems/queens/minizinc/datafiles/10.fzn -f -r",
      "mean": 0.00518898950582677,
      "stddev": 0.0031378881217643466,
      "median": 0.004142538120000001,
      "user": 0.004729424661417319,
      "system": 0.00046936434645669303,
      "min": 0.0024320921200000002,
      "max": 0.030212653120000002,
      "parameters": {
        "n": "10"
      }
    },
    {
      "command": "Oxiflex Problems/queens/minizinc/datafiles/10.fzn -f",
      "mean": 0.00631613293501341,
      "stddev": 0.0008176465994244071,
      "median": 0.00592810012,
      "user": 0.005835210026809647,
      "system": 0.0004912269705093831,
      "min": 0.0055165041200000015,
      "max": 0.009870545120000001,
      "parameters": {
        "n": "10"
      }
    },
    {
      "command": "Oxiflex Problems/queens/minizinc/datafiles/12.fzn -n -r",
      "mean": 0.013839876430704973,
      "stddev": 0.01743161275701126,
      "median": 0.00774342012,
      "user": 0.013115563916449075,
      "system": 0.0007195558224543079,
      "min": 0.0019856531200000004,
      "max": 0.13620748712,
      "parameters": {
        "n": "12"
      }
    },
    {
      "command": "Oxiflex Problems/queens/minizinc/datafiles/12.fzn -n",
      "mean": 0.0034471565810303834,
      "stddev": 0.0006074217796119511,
      "median": 0.00319998612,
      "user": 0.0029355286129458384,
      "system": 0.0005400941611624836,
      "min": 0.0028945281200000003,
      "max": 0.0064957281200000005,
      "parameters": {
        "n": "12"
      }
    },
    {
      "command": "Oxiflex Problems/queens/minizinc/datafiles/12.fzn -f -r",
      "mean": 0.010676790863538762,
      "stddev": 0.00897888808891693,
      "median": 0.007585398120000001,
      "user": 0.010057526838966206,
      "system": 0.0006298404373757453,
      "min": 0.00399495712,
      "max": 0.07522316912,
      "parameters": {
        "n": "12"
      }
    },
    {
      "command": "Oxiflex Problems/queens/minizinc/datafiles/12.fzn -f",
      "mean": 0.00594117821690722,
      "stddev": 0.0009069770274227684,
      "median": 0.005507686120000001,
      "user": 0.005368965567010308,
      "system": 0.000560013154639175,
      "min": 0.005058808120000001,
      "max": 0.01077529112,
      "parameters": {
        "n": "12"
      }
    },
    {
      "command": "Oxiflex Problems/queens/minizinc/datafiles/14.fzn -n -r",
      "mean": 0.03839102237278809,
      "stddev": 0.06134380107335769,
      "median": 0.01839533712,
      "user": 0.03757231390334573,
      "system": 0.0007171703345724906,
      "min": 0.0027796431200000004,
      "max": 0.5437226671200001,
      "parameters": {
        "n": "14"
      }
    },
    {
      "command": "Oxiflex Problems/queens/minizinc/datafiles/14.fzn -n",
      "mean": 0.03066652172638299,
      "stddev": 0.003013746977782392,
      "median": 0.029855988120000003,
      "user": 0.029706058723404264,
      "system": 0.0009134161702127658,
      "min": 0.027014127120000002,
      "max": 0.04446663112,
      "parameters": {
        "n": "14"
      }
    },
    {
      "command": "Oxiflex Problems/queens/minizinc/datafiles/14.fzn -f -r",
      "mean": 0.02646245325513513,
      "stddev": 0.022100278333767178,
      "median": 0.019127425120000003,
      "user": 0.025812904324324325,
      "system": 0.0006339951351351352,
      "min": 0.010465747120000002,
      "max": 0.13695942212,
      "parameters": {
        "n": "14"
      }
    },
    {
      "command": "Oxiflex Problems/queens/minizinc/datafiles/14.fzn -f",
      "mean": 0.021907518176338035,
      "stddev": 0.0019821743843136414,
      "median": 0.02158357912,
      "user": 0.021110819436619726,
      "system": 0.0007036838028169014,
      "min": 0.01951347612,
      "max": 0.031121452120000004,
      "parameters": {
        "n": "14"
      }
    },
    {
      "command": "Oxiflex Problems/queens/minizinc/datafiles/16.fzn -n -r",
      "mean": 0.08863043505537413,
      "stddev": 0.18497170941441501,
      "median": 0.030400486620000004,
      "user": 0.08773013782312933,
      "system": 0.0007950002040816327,
      "min": 0.0035959421200000004,
      "max": 1.91954472512,
      "parameters": {
        "n": "16"
      }
    },
    {
      "command": "Oxiflex Problems/queens/minizinc/datafiles/16.fzn -n",
      "mean": 0.004036190460909089,
      "stddev": 0.0006675559771943256,
      "median": 0.0037536391200000004,
      "user": 0.0033484181493506466,
      "system": 0.0007122355844155845,
      "min": 0.0034441341200000006,
      "max": 0.00660814212,
      "parameters": {
        "n": "16"
      }
    },
    {
      "command": "Oxiflex Problems/queens/minizinc/datafiles/16.fzn -f -r",
      "mean": 0.04694839441090909,
      "stddev": 0.10046631278381873,
      "median": 0.021468568120000003,
      "user": 0.04592494969696967,
      "system": 0.0009569430303030304,
      "min": 0.012668865120000001,
      "max": 1.1090565561199999,
      "parameters": {
        "n": "16"
      }
    },
    {
      "command": "Oxiflex Problems/queens/minizinc/datafiles/16.fzn -f",
      "mean": 0.013370739832041886,
      "stddev": 0.0014601889485555799,
      "median": 0.013001381120000002,
      "user": 0.012615124502617802,
      "system": 0.000749900104712042,
      "min": 0.011689125120000001,
      "max": 0.02328595312,
      "parameters": {
        "n": "16"
      }
    },
    {
      "command": "Oxiflex Problems/queens/minizinc/datafiles/18.fzn -n -r",
      "mean": 0.839299345360741,
      "stddev": 4.906215034069344,
      "median": 0.061689524120000006,
      "user": 0.8384421540740742,
      "system": 0.0005433566666666666,
      "min": 0.00616657812,
      "max": 36.18431274812,
      "parameters": {
        "n": "18"
      }
    },
    {
      "command": "Oxiflex Problems/queens/minizinc/datafiles/18.fzn -n",
      "mean": 0.017828866324081635,
      "stddev": 0.0021464651134834854,
      "median": 0.017230223120000002,
      "user": 0.016971580000000003,
      "system": 0.0008073561904761902,
      "min": 0.01546699512,
      "max": 0.02814489212,
      "parameters": {
        "n": "18"
      }
    },
    {
      "command": "Oxiflex Problems/queens/minizinc/datafiles/18.fzn -f -r",
      "mean": 0.07769908202265487,
      "stddev": 0.10731212832825134,
      "median": 0.04163958712,
      "user": 0.07656301362831856,
      "system": 0.0008373812389380533,
      "min": 0.01927378612,
      "max": 0.6948325591200001,
      "parameters": {
        "n": "18"
      }
    },
    {
      "command": "Oxiflex Problems/queens/minizinc/datafiles/18.fzn -f",
      "mean": 0.024487402016825383,
      "stddev": 0.0019739899387603206,
      "median": 0.024260452120000005,
      "user": 0.023630945079365074,
      "system": 0.0008002704761904761,
      "min": 0.02172929012,
      "max": 0.030441046120000002,
      "parameters": {
        "n": "18"
      }
    },
    {
      "command": "Oxiflex Problems/queens/minizinc/datafiles/20.fzn -n -r",
      "mean": 0.7572564872191375,
      "stddev": 3.3775016668441635,
      "median": 0.12930321911999998,
      "user": 0.7554785886206897,
      "system": 0.001151079568965517,
      "min": 0.006645093120000001,
      "max": 40.567521210120006,
      "parameters": {
        "n": "20"
      }
    },
    {
      "command": "Oxiflex Problems/queens/minizinc/datafiles/20.fzn -n",
      "mean": 0.020976488986197177,
      "stddev": 0.002192935196038655,
      "median": 0.02058490962,
      "user": 0.02012695323943663,
      "system": 0.0008043429577464789,
      "min": 0.01809074012,
      "max": 0.02833638612,
      "parameters": {
        "n": "20"
      }
    },
    {
      "command": "Oxiflex Problems/queens/minizinc/datafiles/20.fzn -f -r",
      "mean": 0.19748856892882352,
      "stddev": 0.6639665726724492,
      "median": 0.055253834120000005,
      "user": 0.19593393294117645,
      "system": 0.0013681347058823528,
      "min": 0.029465911120000004,
      "max": 4.75910887712,
      "parameters": {
        "n": "20"
      }
    },
    {
      "command": "Oxiflex Problems/queens/minizinc/datafiles/20.fzn -f",
      "mean": 0.03571716393707318,
      "stddev": 0.0022021485716872346,
      "median": 0.035536377120000004,
      "user": 0.034857787317073154,
      "system": 0.0007798919512195122,
      "min": 0.03201414012,
      "max": 0.042029018120000004,
      "parameters": {
        "n": "20"
      }
    }
  ]
}
